skrift/__init__.py
skrift/__main__.py
skrift/alembic.ini
skrift/asgi.py
skrift/cli.py
skrift/config.py
skrift/admin/__init__.py
skrift/admin/controller.py
skrift/admin/navigation.py
skrift/alembic/env.py
skrift/alembic/script.py.mako
skrift/alembic/versions/20260120_210154_09b0364dbb7b_initial_schema.py
skrift/alembic/versions/20260122_152744_0b7c927d2591_add_roles_and_permissions.py
skrift/alembic/versions/20260122_172836_cdf734a5b847_add_sa_orm_sentinel_column.py
skrift/alembic/versions/20260122_175637_a9c55348eae7_remove_page_type_column.py
skrift/alembic/versions/20260122_200000_add_settings_table.py
skrift/alembic/versions/20260129_add_oauth_accounts.py
skrift/alembic/versions/20260129_add_provider_metadata.py
skrift/auth/__init__.py
skrift/auth/guards.py
skrift/auth/roles.py
skrift/auth/services.py
skrift/controllers/__init__.py
skrift/controllers/auth.py
skrift/controllers/web.py
skrift/db/__init__.py
skrift/db/base.py
skrift/db/models/__init__.py
skrift/db/models/oauth_account.py
skrift/db/models/page.py
skrift/db/models/role.py
skrift/db/models/setting.py
skrift/db/models/user.py
skrift/db/services/__init__.py
skrift/db/services/oauth_service.py
skrift/db/services/page_service.py
skrift/db/services/setting_service.py
skrift/lib/__init__.py
skrift/lib/exceptions.py
skrift/lib/markdown.py
skrift/lib/template.py
skrift/setup/__init__.py
skrift/setup/config_writer.py
skrift/setup/controller.py
skrift/setup/middleware.py
skrift/setup/providers.py
skrift/setup/state.py
skrift/static/css/style.css
skrift/templates/base.html
skrift/templates/error-404.html
skrift/templates/error-500.html
skrift/templates/error.html
skrift/templates/index.html
skrift/templates/page.html
skrift/templates/admin/admin.html
skrift/templates/admin/base.html
skrift/templates/admin/pages/edit.html
skrift/templates/admin/pages/list.html
skrift/templates/admin/settings/site.html
skrift/templates/admin/users/list.html
skrift/templates/admin/users/roles.html
skrift-0.1.0a14.dist-info/METADATA
skrift-0.1.0a14.dist-info/WHEEL
skrift-0.1.0a14.dist-info/entry_points.txt
skrift-0.1.0a14.dist-info/RECORD
