Metadata-Version: 2.4
Name: skrift
Version: 0.1.0a14
Summary: A lightweight async Python CMS for crafting modern websites
Requires-Python: >=3.13
Requires-Dist: advanced-alchemy>=0.26.0
Requires-Dist: aiosqlite>=0.20.0
Requires-Dist: alembic>=1.14.0
Requires-Dist: asyncpg>=0.30.0
Requires-Dist: httpx>=0.28.0
Requires-Dist: litestar[cryptography,jinja,standard]>=2.14.0
Requires-Dist: markdown-it-py>=3.0.0
Requires-Dist: mdit-py-plugins>=0.4.0
Requires-Dist: pydantic-settings>=2.7.0
Requires-Dist: python-dotenv>=1.0.0
Requires-Dist: pyyaml>=6.0.0
Requires-Dist: ruamel-yaml>=0.18.0
Requires-Dist: sqlalchemy[asyncio]>=2.0.36
Requires-Dist: uvicorn>=0.34.0
Provides-Extra: docs
Requires-Dist: zensical>=0.0.19; extra == 'docs'
